pgn_manager/__init__.py
pgn_manager/pfilter.py
pgn_manager/pmanager.py
pgn_manager-1.3.2.dist-info/METADATA
pgn_manager-1.3.2.dist-info/WHEEL
pgn_manager-1.3.2.dist-info/top_level.txt
pgn_manager-1.3.2.dist-info/RECORD
