Metadata-Version: 2.1
Name: pgn-manager
Version: 1.3.2
Summary: library for managing pgn files
Author: Luca Canali
Author-email: lucacanali.dev@gmail.com
Requires-Dist: python-chess
